flask_seek/__init__.py
flask_seek/factory.py
flask_seek/register.py
flask_seek/util.py
flask_seek-0.2.1.dist-info/LICENSE
flask_seek-0.2.1.dist-info/METADATA
flask_seek-0.2.1.dist-info/WHEEL
flask_seek-0.2.1.dist-info/top_level.txt
flask_seek-0.2.1.dist-info/RECORD
