Metadata-Version: 2.1
Name: flask-seek
Version: 0.2.1
Summary: An flask extension to make your code more elegant
Home-page: https://github.com/ShangSky/flask-seek
Author: shangsky
Author-email: t_c_y@outlook.com
Maintainer: shangsky
Maintainer-email: t_c_y@outlook.com
License: MIT
Platform: all
Classifier: Development Status :: 4 - Beta
Classifier: Operating System :: OS Independent
Classifier: Intended Audience :: Developers
Classifier: License :: OSI Approved :: MIT License
Classifier: Programming Language :: Python :: 3.6
Classifier: Programming Language :: Python :: 3.7
Classifier: Programming Language :: Python :: 3.8
Classifier: Programming Language :: Python :: 3.9
Classifier: Topic :: Software Development :: Libraries
Requires-Python: >=3.6
License-File: LICENSE
Requires-Dist: flask (>=1.1.0)
